s3push/__init__.py
s3push/connector.py
s3push/eraser.py
s3push/progress.py
s3push/uploader.py
s3push-2019.10.14.dist-info/METADATA
s3push-2019.10.14.dist-info/RECORD
s3push-2019.10.14.dist-info/WHEEL
s3push-2019.10.14.dist-info/entry_points.txt
s3push-2019.10.14.dist-info/top_level.txt
