Metadata-Version: 2.1
Name: s3push
Version: 2019.10.14
Summary: Upload directories to AWS S3
Home-page: https://github.com/vduseev/s3push
Author: Vagiz Duseev
Author-email: vagiz@duseev.com
License: UNKNOWN
Keywords: aws s3 static website deployment directories folder upload push publish
Platform: UNKNOWN
Classifier: Development Status :: 4 - Beta
Classifier: Intended Audience :: Developers
Classifier: Topic :: Software Development :: Build Tools
Classifier: License :: OSI Approved :: MIT License
Classifier: Programming Language :: Python :: 3.6
Provides-Extra: dev
Requires-Dist: boto3
Provides-Extra: dev
Requires-Dist: twine; extra == 'dev'
Requires-Dist: wheels; extra == 'dev'
